{
  "global": {
    "spectrum": {
      "gray": {
        "50": {
          "value": "#fbfbfb",
          "type": "color"
        },
        "100": {
          "value": "#f3f3f3",
          "type": "color"
        },
        "200": {
          "value": "#e6e6e6",
          "type": "color"
        },
        "300": {
          "value": "#b4b4b4",
          "type": "color"
        },
        "400": {
          "value": "#9b9b9b",
          "type": "color"
        },
        "500": {
          "value": "#818183",
          "type": "color"
        },
        "600": {
          "value": "#68686a",
          "type": "color"
        },
        "700": {
          "value": "#4f4f51",
          "type": "color"
        },
        "800": {
          "value": "#363638",
          "type": "color"
        },
        "900": {
          "value": "#1d1d1f",
          "type": "color"
        },
        "1000": {
          "value": "#000000",
          "type": "color"
        },
        "000": {
          "value": "#ffffff",
          "type": "color"
        }
      },
      "red": {
        "100": {
          "value": "#ffe5e7",
          "type": "color"
        },
        "200": {
          "value": "#ffc2c6",
          "type": "color"
        },
        "300": {
          "value": "#ff9ea5",
          "type": "color"
        },
        "400": {
          "value": "#f96c73",
          "type": "color"
        },
        "500": {
          "value": "#f1465a",
          "type": "color"
        },
        "600": {
          "value": "#e32144",
          "type": "color"
        },
        "700": {
          "value": "#be1332",
          "type": "color"
        },
        "800": {
          "value": "#990620",
          "type": "color"
        },
        "900": {
          "value": "#650113",
          "type": "color"
        },
        "1000": {
          "value": "#320109",
          "type": "color"
        },
        "000": {
          "value": "#fff5f5",
          "type": "color"
        }
      },
      "blue": {
        "100": {
          "value": "#c1ebf6",
          "type": "color"
        },
        "200": {
          "value": "#96ddef",
          "type": "color"
        },
        "300": {
          "value": "#6ad0e9",
          "type": "color"
        },
        "400": {
          "value": "#3fc2e2",
          "type": "color"
        },
        "500": {
          "value": "#14b4dc",
          "type": "color"
        },
        "600": {
          "value": "#169bbc",
          "type": "color"
        },
        "700": {
          "value": "#17829d",
          "type": "color"
        },
        "800": {
          "value": "#18697e",
          "type": "color"
        },
        "900": {
          "value": "#1a4f5e",
          "type": "color"
        },
        "1000": {
          "value": "#1b363f",
          "type": "color"
        },
        "000": {
          "value": "#ecf9fc",
          "type": "color"
        }
      },
      "green": {
        "100": {
          "value": "#bbf1df",
          "type": "color"
        },
        "200": {
          "value": "#8ce7c9",
          "type": "color"
        },
        "300": {
          "value": "#5eddb4",
          "type": "color"
        },
        "400": {
          "value": "#2fd39e",
          "type": "color"
        },
        "500": {
          "value": "#00c988",
          "type": "color"
        },
        "600": {
          "value": "#00ad76",
          "type": "color"
        },
        "700": {
          "value": "#007552",
          "type": "color"
        },
        "800": {
          "value": "#005940",
          "type": "color"
        },
        "900": {
          "value": "#003d2e",
          "type": "color"
        },
        "1000": {
          "value": "#00291f",
          "type": "color"
        },
        "000": {
          "value": "#f3fcf9",
          "type": "color"
        }
      },
      "yellow": {
        "100": {
          "value": "#ffeebe",
          "type": "color"
        },
        "200": {
          "value": "#ffe397",
          "type": "color"
        },
        "300": {
          "value": "#ffd971",
          "type": "color"
        },
        "400": {
          "value": "#ffce4a",
          "type": "color"
        },
        "500": {
          "value": "#ffc424",
          "type": "color"
        },
        "600": {
          "value": "#ffad1f",
          "type": "color"
        },
        "700": {
          "value": "#fa8900",
          "type": "color"
        },
        "800": {
          "value": "#e55c00",
          "type": "color"
        },
        "900": {
          "value": "#c73f00",
          "type": "color"
        },
        "1000": {
          "value": "#752100",
          "type": "color"
        },
        "000": {
          "value": "#fff8e4",
          "type": "color"
        }
      }
    },
    "docs_shadow": {
      "value": {
        "color": "#00000026",
        "type": "dropShadow",
        "x": "0",
        "y": "4",
        "blur": "6",
        "spread": "0"
      },
      "type": "boxShadow"
    },
    "small": {
      "15": {
        "value": {
          "color": "#00000026",
          "type": "dropShadow",
          "x": "0",
          "y": "0",
          "blur": "30",
          "spread": "0"
        },
        "type": "boxShadow"
      },
      "50": {
        "value": {
          "color": "#00000080",
          "type": "dropShadow",
          "x": "0",
          "y": "0",
          "blur": "30",
          "spread": "0"
        },
        "type": "boxShadow"
      }
    },
    "large": {
      "15": {
        "value": {
          "color": "#00000026",
          "type": "dropShadow",
          "x": "0",
          "y": "0",
          "blur": "150",
          "spread": "0"
        },
        "type": "boxShadow"
      },
      "85": {
        "value": {
          "color": "#000000d9",
          "type": "dropShadow",
          "x": "0",
          "y": "0",
          "blur": "100",
          "spread": "0"
        },
        "type": "boxShadow"
      }
    },
    "extra-large": {
      "15": {
        "value": {
          "color": "#00000026",
          "type": "dropShadow",
          "x": "0",
          "y": "0",
          "blur": "30",
          "spread": "0"
        },
        "type": "boxShadow"
      },
      "100": {
        "value": {
          "color": "#000000",
          "type": "dropShadow",
          "x": "0",
          "y": "0",
          "blur": "30",
          "spread": "0"
        },
        "type": "boxShadow"
      }
    },
    "fontFamilies": {
      "sf-compact": {
        "value": "SF Compact",
        "type": "fontFamilies"
      },
      "degular": {
        "value": "Degular",
        "type": "fontFamilies"
      },
      "neue-haas-unica": {
        "value": "Neue Haas Unica W1G",
        "type": "fontFamilies"
      }
    },
    "lineHeights": {
      "0": {
        "value": "16",
        "type": "lineHeights"
      },
      "1": {
        "value": "20",
        "type": "lineHeights"
      },
      "2": {
        "value": "22",
        "type": "lineHeights"
      },
      "3": {
        "value": "24",
        "type": "lineHeights"
      },
      "4": {
        "value": "34",
        "type": "lineHeights"
      },
      "5": {
        "value": "44",
        "type": "lineHeights"
      },
      "6": {
        "value": "52",
        "type": "lineHeights"
      },
      "7": {
        "value": "118",
        "type": "lineHeights"
      }
    },
    "fontWeights": {
      "sf-compact-1": {
        "value": "medium",
        "type": "fontWeights"
      },
      "sf-compact-2": {
        "value": "semibold",
        "type": "fontWeights"
      },
      "sf-compact-3": {
        "value": "bold",
        "type": "fontWeights"
      },
      "degular-0": {
        "value": "Thin",
        "type": "fontWeights"
      },
      "degular-1": {
        "value": "Semibold",
        "type": "fontWeights"
      },
      "sf-compact-0": {
        "value": "regular",
        "type": "fontWeights"
      },
      "sf-compact-4": {
        "value": "regular italic",
        "type": "fontWeights"
      },
      "neue-haas-unica-1": {
        "value": "Thin",
        "type": "fontWeights"
      },
      "neue-haas-unica-2": {
        "value": "Regular",
        "type": "fontWeights"
      },
      "neue-haas-unica-3": {
        "value": "Bold",
        "type": "fontWeights"
      },
      "neue-haas-unica-4": {
        "value": "Medium",
        "type": "fontWeights"
      },
      "neue-haas-unica-5": {
        "value": "Bold",
        "type": "fontWeights"
      },
      "neue-haas-unica-6": {
        "value": "Heavy",
        "type": "fontWeights"
      },
      "neue-haas-unica-7": {
        "value": "Italic",
        "type": "fontWeights"
      }
    },
    "fontSize": {
      "0": {
        "value": "14",
        "type": "fontSizes"
      },
      "1": {
        "value": "16",
        "type": "fontSizes"
      },
      "2": {
        "value": "18",
        "type": "fontSizes"
      },
      "3": {
        "value": "22",
        "type": "fontSizes"
      },
      "4": {
        "value": "30",
        "type": "fontSizes"
      },
      "5": {
        "value": "40",
        "type": "fontSizes"
      },
      "6": {
        "value": "48",
        "type": "fontSizes"
      },
      "8": {
        "value": "114",
        "type": "fontSizes"
      }
    },
    "letterSpacing": {
      "0": {
        "value": "0",
        "type": "letterSpacing"
      },
      "1": {
        "value": "0%",
        "type": "letterSpacing"
      }
    },
    "paragraphSpacing": {
      "0": {
        "value": "0",
        "type": "paragraphSpacing"
      }
    },
    "H1": {
      "value": {
        "fontFamily": "$fontFamilies.neue-haas-unica",
        "fontWeight": "$fontWeights.neue-haas-unica-1",
        "lineHeight": "$lineHeights.7",
        "fontSize": "$fontSize.8",
        "letterSpacing": "$letterSpacing.0",
        "paragraphSpacing": "$paragraphSpacing.0",
        "textCase": "$textCase.none",
        "textDecoration": "$textDecoration.none"
      },
      "type": "typography"
    },
    "H2": {
      "value": {
        "fontFamily": "$fontFamilies.neue-haas-unica",
        "fontWeight": "$fontWeights.neue-haas-unica-4",
        "lineHeight": "$lineHeights.6",
        "fontSize": "$fontSize.6",
        "letterSpacing": "$letterSpacing.0",
        "paragraphSpacing": "$paragraphSpacing.0",
        "textCase": "$textCase.none",
        "textDecoration": "$textDecoration.none"
      },
      "type": "typography"
    },
    "H3": {
      "value": {
        "fontFamily": "$fontFamilies.neue-haas-unica",
        "fontWeight": "$fontWeights.neue-haas-unica-6",
        "lineHeight": "$lineHeights.5",
        "fontSize": "$fontSize.5",
        "letterSpacing": "$letterSpacing.0",
        "paragraphSpacing": "$paragraphSpacing.0",
        "textCase": "$textCase.none",
        "textDecoration": "$textDecoration.none"
      },
      "type": "typography"
    },
    "textCase": {
      "none": {
        "value": "none",
        "type": "textCase"
      }
    },
    "textDecoration": {
      "none": {
        "value": "none",
        "type": "textDecoration"
      }
    },
    "H4": {
      "value": {
        "fontFamily": "$fontFamilies.neue-haas-unica",
        "fontWeight": "$fontWeights.neue-haas-unica-6",
        "lineHeight": "$lineHeights.4",
        "fontSize": "$fontSize.4",
        "letterSpacing": "0%",
        "paragraphSpacing": "0",
        "textDecoration": "none",
        "textCase": "none"
      },
      "type": "typography"
    },
    "H5": {
      "value": {
        "fontFamily": "$fontFamilies.neue-haas-unica",
        "fontWeight": "$fontWeights.neue-haas-unica-6",
        "lineHeight": "$lineHeights.3",
        "fontSize": "$fontSize.3",
        "letterSpacing": "0%",
        "paragraphSpacing": "0",
        "textDecoration": "none",
        "textCase": "none"
      },
      "type": "typography"
    },
    "Body-XL-Medium": {
      "value": {
        "fontFamily": "$fontFamilies.neue-haas-unica",
        "fontWeight": "$fontWeights.neue-haas-unica-4",
        "lineHeight": "$lineHeights.2",
        "fontSize": "$fontSize.2",
        "letterSpacing": "0%",
        "paragraphSpacing": "0",
        "textDecoration": "none",
        "textCase": "none"
      },
      "type": "typography"
    },
    "Body-XL-Regular": {
      "value": {
        "fontFamily": "$fontFamilies.neue-haas-unica",
        "fontWeight": "$fontWeights.neue-haas-unica-2",
        "lineHeight": "$lineHeights.2",
        "fontSize": "$fontSize.2",
        "letterSpacing": "0%",
        "paragraphSpacing": "0",
        "textDecoration": "none",
        "textCase": "none"
      },
      "type": "typography"
    },
    "Body-Main": {
      "value": {
        "fontFamily": "$fontFamilies.neue-haas-unica",
        "fontWeight": "$fontWeights.neue-haas-unica-2",
        "lineHeight": "$lineHeights.1",
        "fontSize": "$fontSize.1",
        "letterSpacing": "0%",
        "paragraphSpacing": "0",
        "textDecoration": "none",
        "textCase": "none"
      },
      "type": "typography"
    },
    "Body-Main-Bold": {
      "value": {
        "fontFamily": "$fontFamilies.neue-haas-unica",
        "fontWeight": "$fontWeights.neue-haas-unica-3",
        "lineHeight": "$lineHeights.1",
        "fontSize": "$fontSize.1",
        "letterSpacing": "0%",
        "paragraphSpacing": "0",
        "textDecoration": "none",
        "textCase": "none"
      },
      "type": "typography"
    },
    "Body-Main-Semibold": {
      "value": {
        "fontFamily": "$fontFamilies.neue-haas-unica",
        "fontWeight": "$fontWeights.neue-haas-unica-4",
        "lineHeight": "$lineHeights.1",
        "fontSize": "$fontSize.1",
        "letterSpacing": "0%",
        "paragraphSpacing": "0",
        "textDecoration": "none",
        "textCase": "none"
      },
      "type": "typography"
    },
    "Instructions": {
      "value": {
        "fontFamily": "$fontFamilies.neue-haas-unica",
        "fontWeight": "$fontWeights.neue-haas-unica-7",
        "lineHeight": "$lineHeights.1",
        "fontSize": "$fontSize.1",
        "letterSpacing": "0%",
        "paragraphSpacing": "0",
        "textDecoration": "none",
        "textCase": "none"
      },
      "type": "typography"
    },
    "Buttons-Details": {
      "value": {
        "fontFamily": "$fontFamilies.neue-haas-unica",
        "fontWeight": "$fontWeights.neue-haas-unica-2",
        "lineHeight": "$lineHeights.0",
        "fontSize": "$fontSize.0",
        "letterSpacing": "0%",
        "paragraphSpacing": "0",
        "textDecoration": "none",
        "textCase": "none"
      },
      "type": "typography"
    },
    "Buttons-Details-Bold": {
      "value": {
        "fontFamily": "$fontFamilies.neue-haas-unica",
        "fontWeight": "$fontWeights.neue-haas-unica-3",
        "lineHeight": "$lineHeights.0",
        "fontSize": "$fontSize.0",
        "letterSpacing": "0%",
        "paragraphSpacing": "0",
        "textDecoration": "none",
        "textCase": "none"
      },
      "type": "typography"
    },
    "consistent": {
      "consistent-white": {
        "value": "{spectrum.gray.000}",
        "type": "color"
      },
      "consistent-black": {
        "value": "{spectrum.gray.1000}",
        "type": "color"
      }
    },
    "featuredContext": {
      "featuredContext-primary": {
        "value": "{consistent.consistent-black}",
        "type": "color"
      },
      "featuredContext-secondary": {
        "value": "{consistent.consistent-white}",
        "type": "color"
      }
    }
  },
  "dark": {
    "icon": {
      "icon-primary": {
        "value": "{spectrum.gray.000}",
        "type": "color"
      },
      "icon-secondary": {
        "value": "{spectrum.gray.1000}",
        "type": "color"
      }
    },
    "button": {
      "button-primary": {
        "value": "{spectrum.gray.000}",
        "type": "color"
      },
      "button-secondary": {
        "value": "{spectrum.gray.1000}",
        "type": "color"
      },
      "button-disabled": {
        "value": "{spectrum.gray.400}",
        "type": "color"
      }
    },
    "surface": {
      "surface-primary": {
        "value": "{spectrum.gray.900}",
        "type": "color"
      },
      "surface-secondary": {
        "value": "{spectrum.gray.50}",
        "type": "color"
      },
      "surface-tertiary": {
        "value": "{spectrum.gray.1000}",
        "type": "color"
      }
    },
    "text": {
      "text-primary": {
        "value": "{spectrum.gray.000}",
        "type": "color"
      },
      "text-secondary": {
        "value": "{spectrum.gray.1000}",
        "type": "color"
      },
      "text-tertiary": {
        "value": "{spectrum.gray.600}",
        "type": "color"
      }
    },
    "border": {
      "border-primary": {
        "value": "{spectrum.gray.600}",
        "type": "color"
      }
    },
    "input": {
      "input-primary": {
        "value": "{spectrum.gray.000}",
        "type": "color"
      },
      "input-secondary": {
        "value": "{spectrum.gray.700}",
        "type": "color"
      }
    }
  },
  "light": {
    "icon": {
      "icon-primary": {
        "value": "{spectrum.gray.1000}",
        "type": "color"
      },
      "icon-secondary": {
        "value": "{spectrum.gray.000}",
        "type": "color"
      }
    },
    "button": {
      "button-primary": {
        "value": "{spectrum.gray.1000}",
        "type": "color"
      },
      "button-secondary": {
        "value": "{spectrum.gray.000}",
        "type": "color"
      },
      "button-disabled": {
        "value": "{spectrum.gray.400}",
        "type": "color"
      }
    },
    "surface": {
      "surface-primary": {
        "value": "{spectrum.gray.50}",
        "type": "color"
      },
      "surface-secondary": {
        "value": "{spectrum.gray.900}",
        "type": "color"
      },
      "surface-tertiary": {
        "value": "{spectrum.gray.000}",
        "type": "color"
      }
    },
    "text": {
      "text-primary": {
        "value": "{spectrum.gray.1000}",
        "type": "color"
      },
      "text-secondary": {
        "value": "{spectrum.gray.000}",
        "type": "color"
      },
      "text-tertiary": {
        "value": "{spectrum.gray.600}",
        "type": "color"
      }
    },
    "border": {
      "border-primary": {
        "value": "{spectrum.gray.900}",
        "type": "color"
      }
    },
    "input": {
      "input-primary": {
        "value": "{spectrum.gray.1000}",
        "type": "color"
      },
      "input-secondary": {
        "value": "{spectrum.gray.300}",
        "type": "color"
      }
    }
  },
  "user's featured color": {
    "featuredContext": {
      "featuredContext-primary": {
        "value": "#3f9ff5",
        "type": "color"
      },
      "featuredContext-secondary": {
        "value": "#CdaF75",
        "type": "color"
      }
    }
  },
  "$themes": [
    {
      "id": "11771dbe870ed6a87a6cb198302b60f67826f274",
      "name": "Dark Mode",
      "selectedTokenSets": {
        "global": "enabled",
        "dark": "enabled",
        "light": "disabled",
        "user's featured color": "disabled"
      },
      "$figmaStyleReferences": {
        "icon.icon-primary": "S:257e95bddbdf8a11e4338c4e617905e074f299f8,",
        "icon.icon-secondary": "S:f0c7de75fbb2e0188e178e7432ccb374d1cb3405,",
        "button.button-primary": "S:74310222af6fda213173bdf22977f8f6e810bffa,",
        "button.button-secondary": "S:09d1d4e0fb16eb2bf72d1817bb75f7ce17f569b4,",
        "button.button-disabled": "S:01d916d5b6d01c4ac6540324db571bb9fd341b0a,",
        "surface.surface-primary": "S:94552254e08d421cdaff1c625e3bf8cb518cb854,",
        "surface.surface-secondary": "S:118cb68a75e83a3dfd3cb82db2364df1e2752ee9,",
        "surface.surface-tertiary": "S:6dd9c0df7b4c46d0b3e8887f35fe97675ee4c88b,",
        "text.text-primary": "S:b8f6718109cc340bfbcaaf8f8ac7c0ab85c9d2ba,",
        "text.text-secondary": "S:c37fca065f8ebbcab6dbd25bdcdb5aed9ef66124,",
        "text.text-tertiary": "S:0fff4852462534d8f22dd1fda8f6b0af1da5f7f2,",
        "border.border-primary": "S:46d2f4eeb0c7b4969d1db5fcaf606c577ac12bf8,",
        "input.input-primary": "S:951fa26b03422a606eaea1dca34bccd58a3cffdd,",
        "input.input-secondary": "S:3b32b3aa6044e25a955ee0ed2dbe6edab7695f8b,",
        "spectrum.gray.50": "S:cdc3456acbf237454c8d834941651ce892ebb58d,",
        "spectrum.gray.100": "S:e93aef8dcd4db03d0657dc84ffcde04dd4692dd3,",
        "spectrum.gray.200": "S:216e8a14aabf571562249ee43d8ff24da93af9e2,",
        "spectrum.gray.300": "S:4663b45861d645f6bfe7c43cc473c1cf2da771a0,",
        "spectrum.gray.400": "S:7478b2fd6d9b27b29d76e1a233308711f4a38759,",
        "spectrum.gray.500": "S:06c3ebf4507c6677a0a5fee6a27850e013834f8d,",
        "spectrum.gray.600": "S:643c57aaff5801774def952102167e8b4642093d,",
        "spectrum.gray.700": "S:873693ac7b69a6367d7a4d0dd822822588847428,",
        "spectrum.gray.800": "S:f862c8de2eb820fe557f82f2664d571aaed918c2,",
        "spectrum.gray.900": "S:eb58bfdfd2e4795a0b6d88158f623e83ac1b932a,",
        "spectrum.gray.1000": "S:4695c309a35c54190f1053b7520246a9acb098f1,",
        "spectrum.gray.000": "S:db6fa687cbb71f7406c751fb3f8af43caa9be6c0,",
        "spectrum.red.100": "S:2b486d4e7489080da3b51b01c89d49d7b5fe4384,",
        "spectrum.red.200": "S:67bced8cb2260f1ae4790760731b0bfe54b4fe69,",
        "spectrum.red.300": "S:17e6a246b8a32d7be82177ad529b37f2a911e1e4,",
        "spectrum.red.400": "S:fe2a9a3fb419f7fd95dfb3bb650a07f7102792b5,",
        "spectrum.red.500": "S:7a8e7fe52a8d3236743b0c2a4b0aaa2bbea3f587,",
        "spectrum.red.600": "S:ead51e65672d5f3c77495580ca944291624a3089,",
        "spectrum.red.700": "S:f7131e87501752693f8402325ea878ddbc95c8d8,",
        "spectrum.red.800": "S:73b3677e0202bec4c2d336abc5e9129fc549fcaf,",
        "spectrum.red.900": "S:4dfa4687ad9bb5f3089ec47bfe53b7115403d16f,",
        "spectrum.red.1000": "S:b5e3a7ced5ac35ff960f73fb337246323faed0eb,",
        "spectrum.red.000": "S:3350d874cb863208f79738fb5cca419f4178a4fb,",
        "spectrum.blue.100": "S:b1c6fcd2d926b81bcdad369ce05d879c9e0cecbe,",
        "spectrum.blue.200": "S:a731517ac3e35284eeb218c29fa9b487c52ea9de,",
        "spectrum.blue.300": "S:dc8d0831cadf2f00e42b96e098a282daed8b11c4,",
        "spectrum.blue.400": "S:ece635d4deca74034879548643e6494710383eff,",
        "spectrum.blue.500": "S:63c3dc881e595a2967b9ffcc87cf864d903fbd8e,",
        "spectrum.blue.600": "S:b050580a4ec400fa96deaa6fae77a8b5c132e0c7,",
        "spectrum.blue.700": "S:5fe124bd8212fd12aa9deddc3b1959a7da5de022,",
        "spectrum.blue.800": "S:9b54e631c3942488fdf41a67eaec917f597e4127,",
        "spectrum.blue.900": "S:35af5cd173b2e3252fac2a0f9bb372aa62bbecfc,",
        "spectrum.blue.1000": "S:46611492cf8e9fb0383634abdf5e65ba71e648c2,",
        "spectrum.blue.000": "S:71f04ad49543a269cd0b6408b4c37e9ce8925082,",
        "spectrum.green.100": "S:3e20e036518d5bfe1beb5e6a4845640e9368db2a,",
        "spectrum.green.200": "S:980d665a8a3e7b8ab7cc40291095d55e794d75c4,",
        "spectrum.green.300": "S:b07fb98ef9562ddd3c220dc004b035a281c01e72,",
        "spectrum.green.400": "S:a58f43cddb5772b922ed902b73f504802f910119,",
        "spectrum.green.500": "S:3dc32d4ef409e92fedfe408d9f4a7a3634a38949,",
        "spectrum.green.600": "S:645d17989ddb7f453df8bc96b17b423fb6f0b5bb,",
        "spectrum.green.700": "S:e6c70ff30203018f795775706c2c6a32b65cfc71,",
        "spectrum.green.800": "S:a248c24b873708fb03a42c813ae1e398665b16a2,",
        "spectrum.green.900": "S:8d05f96017cc5f652a776850930202ba541b18ce,",
        "spectrum.green.1000": "S:8b065b0c601efaeeecb3bdf86325aba8ff16b9e2,",
        "spectrum.green.000": "S:c92028737db2ad3c41df5959173f79aa54beeaa8,",
        "spectrum.yellow.100": "S:4ed9c3ea5e33bdafb5dcb5261f9933f463b0dbbd,",
        "spectrum.yellow.200": "S:ef6981757e949a504cf6dbf85730687cc0822cbc,",
        "spectrum.yellow.300": "S:bc6e52c61d565dccb53fb5e99af6d7d3140e6a1f,",
        "spectrum.yellow.400": "S:662e348ede089c79b2de1c5b3ff6710fb2613327,",
        "spectrum.yellow.500": "S:097ec314822de1c516e424d3b3b53b341e720981,",
        "spectrum.yellow.600": "S:e395574820078e3e8a542c4f580ebbacedf49c16,",
        "spectrum.yellow.700": "S:37cb1758e105aa2278a4ea9cf4a0ba9335782b64,",
        "spectrum.yellow.800": "S:544f532069ba7ceca579453f1adf293e12be8fab,",
        "spectrum.yellow.900": "S:c02f481ac530cb072291c78afe05ba8d7e1966bf,",
        "spectrum.yellow.1000": "S:df7ec0dc3bd14cbf3607f6a933ac9aa1ddd74d76,",
        "spectrum.yellow.000": "S:4269f2f9be1c34d76dc7f1f052d011eeccf985c3,",
        "consistent.consistent-white": "S:9dec118c78b1c26172981602e169d5fad7d8383c,",
        "consistent.consistent-black": "S:ffac0ecfb5c1c989f8a40dd5048ca5d041ac597d,",
        "featuredContext.featuredContext-primary": "S:df2782e6ddc872d432be049472fb63b96ac9ede2,",
        "featuredContext.featuredContext-secondary": "S:155b3050bdc192190968deac0277a8049cbfa64b,",
        "H1": "S:8def707ef3a1a5323e299fd4bf2d015632100b5f,",
        "H2": "S:62b77021b3d64d0dfeeeddd3958550f0a32043a7,",
        "H3": "S:5368d92e249baaa5fcd4f43621187301e6bc156f,",
        "H4": "S:5a5b08a61859fa78d7a5c831a39fb025dc03519f,",
        "H5": "S:028fd147b3114296236e7cb18249231cd6ff24df,",
        "Body-XL-Medium": "S:3dd192b523524757c47cd70cae1b8d14a7db7fe9,",
        "Body-XL-Regular": "S:8afa6aabc79a54fe5c644c681d50a5eeb8a7b093,",
        "Body-Main": "S:fc3ed9b567f54f2d1a6aa13bb454be875d47f55e,",
        "Body-Main-Bold": "S:2c77c8d1b4ef45f32fffe3bea3b4cb277de795ce,",
        "Body-Main-Semibold": "S:973999c51d7a3af1b1497188a513c9e1e71bfb4c,",
        "Instructions": "S:232ffba0a8c975816f3920dd855267936fd2edad,",
        "Buttons-Details": "S:0c35a40ff2b8d52e523909a2d81de0265a9158e2,",
        "docs_shadow": "S:0055c731d761f4c51be2ada283565563abbb134b,",
        "small.15": "S:51f9b75b1bec84ea9eb3d957ce3f82c96f8c5100,",
        "small.50": "S:b7e01b477787a0387c95a0a7dfe27ec0faace9ff,",
        "large.15": "S:e5226b34a3bb428ad63bb012590616e22941d865,",
        "large.85": "S:0f2f5779be08b14e876e1b7927d755e9fbb2ca7b,",
        "extra-large.15": "S:bae5b822dae021861cd163a02973607ec07e22fb,",
        "extra-large.100": "S:ed91ddf232f94c373045da1e268018b365351ca9,",
        "Buttons-Details-Bold": "S:e25f54366b8073493185f448b537e8405ddc644e,"
      }
    },
    {
      "id": "2b1595abe14a62ac1703213f52b06a6cb4cb8e77",
      "name": "Light Mode",
      "selectedTokenSets": {
        "global": "enabled",
        "light": "enabled",
        "dark": "disabled",
        "user's featured color": "disabled"
      },
      "$figmaStyleReferences": {
        "icon.icon-primary": "S:257e95bddbdf8a11e4338c4e617905e074f299f8,",
        "icon.icon-secondary": "S:f0c7de75fbb2e0188e178e7432ccb374d1cb3405,",
        "button.button-primary": "S:74310222af6fda213173bdf22977f8f6e810bffa,",
        "button.button-secondary": "S:09d1d4e0fb16eb2bf72d1817bb75f7ce17f569b4,",
        "button.button-disabled": "S:01d916d5b6d01c4ac6540324db571bb9fd341b0a,",
        "surface.surface-primary": "S:94552254e08d421cdaff1c625e3bf8cb518cb854,",
        "surface.surface-secondary": "S:118cb68a75e83a3dfd3cb82db2364df1e2752ee9,",
        "surface.surface-tertiary": "S:6dd9c0df7b4c46d0b3e8887f35fe97675ee4c88b,",
        "text.text-primary": "S:b8f6718109cc340bfbcaaf8f8ac7c0ab85c9d2ba,",
        "text.text-secondary": "S:c37fca065f8ebbcab6dbd25bdcdb5aed9ef66124,",
        "text.text-tertiary": "S:0fff4852462534d8f22dd1fda8f6b0af1da5f7f2,",
        "border.border-primary": "S:46d2f4eeb0c7b4969d1db5fcaf606c577ac12bf8,",
        "input.input-primary": "S:951fa26b03422a606eaea1dca34bccd58a3cffdd,",
        "input.input-secondary": "S:3b32b3aa6044e25a955ee0ed2dbe6edab7695f8b,",
        "spectrum.gray.50": "S:cdc3456acbf237454c8d834941651ce892ebb58d,",
        "spectrum.gray.100": "S:e93aef8dcd4db03d0657dc84ffcde04dd4692dd3,",
        "spectrum.gray.200": "S:216e8a14aabf571562249ee43d8ff24da93af9e2,",
        "spectrum.gray.300": "S:4663b45861d645f6bfe7c43cc473c1cf2da771a0,",
        "spectrum.gray.400": "S:7478b2fd6d9b27b29d76e1a233308711f4a38759,",
        "spectrum.gray.500": "S:06c3ebf4507c6677a0a5fee6a27850e013834f8d,",
        "spectrum.gray.600": "S:643c57aaff5801774def952102167e8b4642093d,",
        "spectrum.gray.700": "S:873693ac7b69a6367d7a4d0dd822822588847428,",
        "spectrum.gray.800": "S:f862c8de2eb820fe557f82f2664d571aaed918c2,",
        "spectrum.gray.900": "S:eb58bfdfd2e4795a0b6d88158f623e83ac1b932a,",
        "spectrum.gray.1000": "S:4695c309a35c54190f1053b7520246a9acb098f1,",
        "spectrum.gray.000": "S:db6fa687cbb71f7406c751fb3f8af43caa9be6c0,",
        "spectrum.red.100": "S:2b486d4e7489080da3b51b01c89d49d7b5fe4384,",
        "spectrum.red.200": "S:67bced8cb2260f1ae4790760731b0bfe54b4fe69,",
        "spectrum.red.300": "S:17e6a246b8a32d7be82177ad529b37f2a911e1e4,",
        "spectrum.red.400": "S:fe2a9a3fb419f7fd95dfb3bb650a07f7102792b5,",
        "spectrum.red.500": "S:7a8e7fe52a8d3236743b0c2a4b0aaa2bbea3f587,",
        "spectrum.red.600": "S:ead51e65672d5f3c77495580ca944291624a3089,",
        "spectrum.red.700": "S:f7131e87501752693f8402325ea878ddbc95c8d8,",
        "spectrum.red.800": "S:73b3677e0202bec4c2d336abc5e9129fc549fcaf,",
        "spectrum.red.900": "S:4dfa4687ad9bb5f3089ec47bfe53b7115403d16f,",
        "spectrum.red.1000": "S:b5e3a7ced5ac35ff960f73fb337246323faed0eb,",
        "spectrum.red.000": "S:3350d874cb863208f79738fb5cca419f4178a4fb,",
        "spectrum.blue.100": "S:b1c6fcd2d926b81bcdad369ce05d879c9e0cecbe,",
        "spectrum.blue.200": "S:a731517ac3e35284eeb218c29fa9b487c52ea9de,",
        "spectrum.blue.300": "S:dc8d0831cadf2f00e42b96e098a282daed8b11c4,",
        "spectrum.blue.400": "S:ece635d4deca74034879548643e6494710383eff,",
        "spectrum.blue.500": "S:63c3dc881e595a2967b9ffcc87cf864d903fbd8e,",
        "spectrum.blue.600": "S:b050580a4ec400fa96deaa6fae77a8b5c132e0c7,",
        "spectrum.blue.700": "S:5fe124bd8212fd12aa9deddc3b1959a7da5de022,",
        "spectrum.blue.800": "S:9b54e631c3942488fdf41a67eaec917f597e4127,",
        "spectrum.blue.900": "S:35af5cd173b2e3252fac2a0f9bb372aa62bbecfc,",
        "spectrum.blue.1000": "S:46611492cf8e9fb0383634abdf5e65ba71e648c2,",
        "spectrum.blue.000": "S:71f04ad49543a269cd0b6408b4c37e9ce8925082,",
        "spectrum.green.100": "S:3e20e036518d5bfe1beb5e6a4845640e9368db2a,",
        "spectrum.green.200": "S:980d665a8a3e7b8ab7cc40291095d55e794d75c4,",
        "spectrum.green.300": "S:b07fb98ef9562ddd3c220dc004b035a281c01e72,",
        "spectrum.green.400": "S:a58f43cddb5772b922ed902b73f504802f910119,",
        "spectrum.green.500": "S:3dc32d4ef409e92fedfe408d9f4a7a3634a38949,",
        "spectrum.green.600": "S:645d17989ddb7f453df8bc96b17b423fb6f0b5bb,",
        "spectrum.green.700": "S:e6c70ff30203018f795775706c2c6a32b65cfc71,",
        "spectrum.green.800": "S:a248c24b873708fb03a42c813ae1e398665b16a2,",
        "spectrum.green.900": "S:8d05f96017cc5f652a776850930202ba541b18ce,",
        "spectrum.green.1000": "S:8b065b0c601efaeeecb3bdf86325aba8ff16b9e2,",
        "spectrum.green.000": "S:c92028737db2ad3c41df5959173f79aa54beeaa8,",
        "spectrum.yellow.100": "S:4ed9c3ea5e33bdafb5dcb5261f9933f463b0dbbd,",
        "spectrum.yellow.200": "S:ef6981757e949a504cf6dbf85730687cc0822cbc,",
        "spectrum.yellow.300": "S:bc6e52c61d565dccb53fb5e99af6d7d3140e6a1f,",
        "spectrum.yellow.400": "S:662e348ede089c79b2de1c5b3ff6710fb2613327,",
        "spectrum.yellow.500": "S:097ec314822de1c516e424d3b3b53b341e720981,",
        "spectrum.yellow.600": "S:e395574820078e3e8a542c4f580ebbacedf49c16,",
        "spectrum.yellow.700": "S:37cb1758e105aa2278a4ea9cf4a0ba9335782b64,",
        "spectrum.yellow.800": "S:544f532069ba7ceca579453f1adf293e12be8fab,",
        "spectrum.yellow.900": "S:c02f481ac530cb072291c78afe05ba8d7e1966bf,",
        "spectrum.yellow.1000": "S:df7ec0dc3bd14cbf3607f6a933ac9aa1ddd74d76,",
        "spectrum.yellow.000": "S:4269f2f9be1c34d76dc7f1f052d011eeccf985c3,",
        "consistent.consistent-white": "S:9dec118c78b1c26172981602e169d5fad7d8383c,",
        "consistent.consistent-black": "S:ffac0ecfb5c1c989f8a40dd5048ca5d041ac597d,",
        "featuredContext.featuredContext-primary": "S:df2782e6ddc872d432be049472fb63b96ac9ede2,",
        "featuredContext.featuredContext-secondary": "S:155b3050bdc192190968deac0277a8049cbfa64b,",
        "H1": "S:8def707ef3a1a5323e299fd4bf2d015632100b5f,",
        "H2": "S:62b77021b3d64d0dfeeeddd3958550f0a32043a7,",
        "H3": "S:5368d92e249baaa5fcd4f43621187301e6bc156f,",
        "H4": "S:5a5b08a61859fa78d7a5c831a39fb025dc03519f,",
        "H5": "S:028fd147b3114296236e7cb18249231cd6ff24df,",
        "Body-XL-Medium": "S:3dd192b523524757c47cd70cae1b8d14a7db7fe9,",
        "Body-XL-Regular": "S:8afa6aabc79a54fe5c644c681d50a5eeb8a7b093,",
        "Body-Main": "S:fc3ed9b567f54f2d1a6aa13bb454be875d47f55e,",
        "Body-Main-Bold": "S:2c77c8d1b4ef45f32fffe3bea3b4cb277de795ce,",
        "Body-Main-Semibold": "S:973999c51d7a3af1b1497188a513c9e1e71bfb4c,",
        "Instructions": "S:232ffba0a8c975816f3920dd855267936fd2edad,",
        "Buttons-Details": "S:0c35a40ff2b8d52e523909a2d81de0265a9158e2,",
        "docs_shadow": "S:0055c731d761f4c51be2ada283565563abbb134b,",
        "small.15": "S:51f9b75b1bec84ea9eb3d957ce3f82c96f8c5100,",
        "small.50": "S:b7e01b477787a0387c95a0a7dfe27ec0faace9ff,",
        "large.15": "S:e5226b34a3bb428ad63bb012590616e22941d865,",
        "large.85": "S:0f2f5779be08b14e876e1b7927d755e9fbb2ca7b,",
        "extra-large.15": "S:bae5b822dae021861cd163a02973607ec07e22fb,",
        "extra-large.100": "S:ed91ddf232f94c373045da1e268018b365351ca9,"
      }
    }
  ],
  "$metadata": {
    "tokenSetOrder": [
      "global",
      "dark",
      "light",
      "user's featured color"
    ]
  }
}